geophysics_analysis/__init__.py
geophysics_analysis/geophysics_analysis.py
geophysics_analysis-0.0.5.dist-info/LICENSE
geophysics_analysis-0.0.5.dist-info/METADATA
geophysics_analysis-0.0.5.dist-info/WHEEL
geophysics_analysis-0.0.5.dist-info/top_level.txt
geophysics_analysis-0.0.5.dist-info/RECORD
