Metadata-Version: 2.1
Name: geophysics-analysis
Version: 0.0.5
Summary: A collection of functions for the analysis of geophysical fields
Home-page: UNKNOWN
Author: Michael Needham
Author-email: m.needham@colostate.edu
License: UNKNOWN
Platform: UNKNOWN
Classifier: Programming Language :: Python :: 3
Classifier: License :: OSI Approved :: MIT License
Classifier: Operating System :: OS Independent
